mol2mesh/__init__.py
mol2mesh/file_parser.py
mol2mesh/mol2mesh.py
mol2mesh/style.py
mol2mesh/surfaces.py
mol2mesh-0.1.1.dist-info/LICENSE
mol2mesh-0.1.1.dist-info/METADATA
mol2mesh-0.1.1.dist-info/WHEEL
mol2mesh-0.1.1.dist-info/entry_points.txt
mol2mesh-0.1.1.dist-info/top_level.txt
mol2mesh-0.1.1.dist-info/RECORD
