Metadata-Version: 2.2
Name: mol2mesh
Version: 0.1.1
Summary: Convert molecular structures into 3D meshes
Author: Ira Novianti
License: MIT License
Project-URL: Repository, https://github.com/iranovianti/mol2mesh
License-File: LICENSE
Requires-Dist: numpy
Requires-Dist: scipy
Requires-Dist: simpy
Requires-Dist: plotly
Requires-Dist: webcolors
Requires-Dist: trimesh
